setup.cfg
setup.py
xunleishare/__init__.py
xunleishare/__main__.py
xunleishare/xunleishare.py
xunleishare.egg-info/PKG-INFO
xunleishare.egg-info/SOURCES.txt
xunleishare.egg-info/dependency_links.txt
xunleishare.egg-info/entry_points.txt
xunleishare.egg-info/requires.txt
xunleishare.egg-info/top_level.txt