Metadata-Version: 1.1
Name: xunleishare
Version: 0.1.4
Summary: Based on the idea of sharing, XunleiShare is a command-line interface tool to directly get download links on Xunlei Lixian servers with the help of the maintainer's Xunlei VIP account. You do not have to acquire a VIP.
Home-page: https://github.com/Chion82/xunlei_share
Author: Chion82
Author-email: sdspeedonion@gmail.com
License: MIT
Keywords: xunlei,xunleishare,thunder
Platform: UNKNOWN
Classifier: Development Status :: 3 - Alpha
Classifier: Programming Language :: Python :: 2
Classifier: Programming Language :: Python :: 2.6
Classifier: Programming Language :: Python :: 2.7
